parselcli/__init__.py
parselcli/cli.py
parselcli/config.py
parselcli/embed.py
parselcli/processors.py
parselcli/prompt/__init__.py
parselcli/prompt/commands.py
parselcli/prompt/completer.py
parselcli/prompt/runner.py
parselcli/prompt/utils.py
parselcli/render/__init__.py
parselcli/render/browser.py
parselcli/render/http.py
parselcli/render/memory.py
parselcli/utils.py
parselcli-1.2.1.dist-info/entry_points.txt
parselcli-1.2.1.dist-info/LICENSE
parselcli-1.2.1.dist-info/WHEEL
parselcli-1.2.1.dist-info/METADATA
parselcli-1.2.1.dist-info/RECORD
