Metadata-Version: 2.1
Name: parselcli
Version: 1.2.1
Summary: CLI interpreter for xpath/css selectors
Home-page: https://scrapecrow.com
License: GPLv3
Author: granitosaurus
Author-email: bernardas.alisauskas@pm.me
Requires-Python: >=3.7,<4.0
Classifier: Environment :: Console
Classifier: Intended Audience :: Developers
Classifier: License :: OSI Approved :: GNU General Public License v3 or later (GPLv3+)
Classifier: License :: Other/Proprietary License
Classifier: Operating System :: POSIX
Classifier: Programming Language :: Python :: 3
Classifier: Programming Language :: Python :: 3.10
Classifier: Programming Language :: Python :: 3.7
Classifier: Programming Language :: Python :: 3.8
Classifier: Programming Language :: Python :: 3.9
Classifier: Topic :: Internet
Provides-Extra: browser
Requires-Dist: Brotli (>=1.0.9,<2.0.0)
Requires-Dist: beautifulsoup4 (>=4.10.0,<5.0.0)
Requires-Dist: click (>=8.0.1,<9.0.0)
Requires-Dist: loguru (>=0.5.3,<0.6.0)
Requires-Dist: nest-asyncio (>=1.5.4,<2.0.0)
Requires-Dist: parsel (>=1.6.0,<2.0.0)
Requires-Dist: playwright (>=1.17.2,<2.0.0); extra == "browser"
Requires-Dist: prompt-toolkit (>=3.0.20,<4.0.0)
Requires-Dist: pyperclip (>=1.8.2,<2.0.0)
Requires-Dist: requests-cache (>=0.9.1,<0.10.0)
Requires-Dist: rich (>=10.11.0,<11.0.0)
Requires-Dist: toml (>=0.10.2,<0.11.0)
Project-URL: Repository, https://github.com/granitosaurus/parsel-cli
